jupyter_nbmodel_client/__init__.py
jupyter_nbmodel_client/_version.py
jupyter_nbmodel_client/agent.py
jupyter_nbmodel_client/client.py
jupyter_nbmodel_client/constants.py
jupyter_nbmodel_client/helpers.py
jupyter_nbmodel_client/model.py
jupyter_nbmodel_client/utils.py
jupyter_nbmodel_client/tests/__init__.py
jupyter_nbmodel_client/tests/_asgi.py
jupyter_nbmodel_client/tests/conftest.py
jupyter_nbmodel_client/tests/test_agent.py
jupyter_nbmodel_client/tests/test_client.py
jupyter_nbmodel_client-0.14.2.dist-info/METADATA
jupyter_nbmodel_client-0.14.2.dist-info/WHEEL
jupyter_nbmodel_client-0.14.2.dist-info/licenses/LICENSE
jupyter_nbmodel_client-0.14.2.dist-info/RECORD
