Metadata-Version: 2.4
Name: jupyter_nbmodel_client
Version: 0.14.2
Project-URL: Home, https://github.com/datalayer/jupyter-nbmodel-client
Author-email: Datalayer <info@datalayer.io>
License: BSD 3-Clause License
License-File: LICENSE
Keywords: Jupyter
Classifier: Framework :: Jupyter
Classifier: License :: OSI Approved :: BSD License
Classifier: Programming Language :: Python
Classifier: Programming Language :: Python :: 3
Requires-Python: >=3.9
Requires-Dist: datalayer-pycrdt==0.12.17
Requires-Dist: jupyter-ydoc==3.0.5
Requires-Dist: nbformat>=5.10.4
Requires-Dist: requests
Requires-Dist: websockets>=15.0.1
Provides-Extra: lint
Requires-Dist: mdformat-gfm>=0.3.5; extra == 'lint'
Requires-Dist: mdformat>0.7; extra == 'lint'
Requires-Dist: pre-commit; extra == 'lint'
Requires-Dist: ruff; extra == 'lint'
Provides-Extra: test
Requires-Dist: hypercorn>=0.16.0; extra == 'test'
Requires-Dist: ipykernel; extra == 'test'
Requires-Dist: jupyter-kernel-client; extra == 'test'
Requires-Dist: jupyter-server-ydoc==2.0.2; extra == 'test'
Requires-Dist: pycrdt-websocket; extra == 'test'
Requires-Dist: pytest-asyncio; extra == 'test'
Requires-Dist: pytest-timeout; extra == 'test'
Requires-Dist: pytest>=7.0; extra == 'test'
Provides-Extra: typing
Requires-Dist: mypy>=0.990; extra == 'typing'
